disdpy.py
disdpy-7.7.7.dist-info/licenses/LICENSE
disdpy-7.7.7.dist-info/METADATA
disdpy-7.7.7.dist-info/WHEEL
disdpy-7.7.7.dist-info/top_level.txt
disdpy-7.7.7.dist-info/RECORD
