Metadata-Version: 2.4
Name: disdpy
Version: 7.7.7
Summary: ееее
Author-email: marfel <nigga@gmail.com>
License: MIT
Requires-Python: >=3.8
License-File: LICENSE
Dynamic: license-file
